[
    {
        "rows": [
            [
                {
                    "name": "name"
                },
                {
                    "name": "image"
                }
            ],
            [
                {
                    "name": "private"
                },
                {
                    "name": "file"
                },
                {
                    "name": "nameOfFile"
                }
            ]
        ],
        "style": "default",
        "label": "Overview"
    },
    {
        "rows": [
            [
                {
                    "name": "colorDepth"
                },
                {
                    "name": "colorSpace"
                }
            ],
            [
                {
                    "name": "width"
                },
                {
                    "name": "height"
                }
            ],
            [
                {
                    "name": "size"
                },
                {
                    "name": "orientation"
                }
            ]
        ],
        "style": "default",
        "dynamicLogicVisible": null,
        "customLabel": "Info"
    }
]